pygcg/GUI_main.py
pygcg/__init__.py
pygcg/_version.py
pygcg/example_config.toml
pygcg/tabs/__init__.py
pygcg/tabs/beams.py
pygcg/tabs/spectrum.py
pygcg/utils/__init__.py
pygcg/utils/icon_checkbox.py
pygcg/utils/misc.py
pygcg/utils/toolbar.py
pygcg/windows/__init__.py
pygcg/windows/base_window.py
pygcg/windows/comments.py
pygcg/windows/search.py
pygcg/windows/settings.py
pyGCG-1.4.dist-info/LICENCE.txt
pyGCG-1.4.dist-info/METADATA
pyGCG-1.4.dist-info/WHEEL
pyGCG-1.4.dist-info/top_level.txt
pyGCG-1.4.dist-info/RECORD
