Metadata-Version: 2.1
Name: pyGCG
Version: 1.4
Summary: A GUI to aid in viewing and classifying NIRISS data products from GLASS-JWST.
Author-email: Peter Watson <peter.watson+pygcg@inaf.it>
Project-URL: Homepage, https://github.com/PJ-Watson/pyGCG
Project-URL: Bug Tracker, https://github.com/PJ-Watson/pyGCG/issues
Classifier: Programming Language :: Python :: 3
Classifier: License :: OSI Approved :: GNU General Public License v3 (GPLv3)
Classifier: Operating System :: OS Independent
Requires-Python: >=3.10
License-File: LICENCE.txt
Requires-Dist: astropy >=5.3
Requires-Dist: numpy >=1.24
Requires-Dist: tomlkit >=0.12
Requires-Dist: customtkinter >=5.2
Requires-Dist: CTkMessageBox >=2.5
Requires-Dist: matplotlib >=3.6
Requires-Dist: tqdm >=4.66
Requires-Dist: photutils >=1.9
